{
  "profileDb": {
    "0": {
      "donor": true,
      "receiver": true,
      "givenNames": "Ash",
      "lastNames": "Ketchup",
      "dateOfBirth": {
        "year": 1966,
        "month": 1,
        "day": 7
      },
      "chronicDiseases": [],
      "updateActions": [
        "given-names updated at 03:54 PM 16-05-2018",
        "last-names updated at 03:54 PM 16-05-2018",
        "ird updated at 03:54 PM 16-05-2018",
        "dob updated at 03:54 PM 16-05-2018"
      ],
      "procedures": [],
      "organsDonating": [
        "BONE_MARROW",
        "HEART",
        "BONE",
        "CONNECTIVE_TISSUE",
        "CORNEA"
      ],
      "organsDonated": [
        "INTESTINE",
        "BONE_MARROW",
        "HEART",
        "BONE",
        "CONNECTIVE_TISSUE",
        "CORNEA",
        "KIDNEY"
      ],
      "organsRequired": [],
      "organsReceived": [],
      "conditions": [],
      "irdNumber": 192676460,
      "timeOfCreation": {
        "date": {
          "year": 2018,
          "month": 5,
          "day": 16
        },
        "time": {
          "hour": 15,
          "minute": 54,
          "second": 21,
          "nano": 251000000
        }
      },
      "lastUpdated": {
        "date": {
          "year": 2018,
          "month": 5,
          "day": 16
        },
        "time": {
          "hour": 15,
          "minute": 54,
          "second": 21,
          "nano": 251000000
        }
      },
      "id": 0,
      "currentMedications": [],
      "historyOfMedication": [],
      "medicationTimestamps": []
    },
    "1": {
      "donor": true,
      "receiver": true,
      "givenNames": "Basashi",
      "lastNames": "Tabetai",
      "dateOfBirth": {
        "year": 1932,
        "month": 9,
        "day": 28
      },
      "chronicDiseases": [],
      "updateActions": [
        "given-names updated at 03:54 PM 16-05-2018",
        "last-names updated at 03:54 PM 16-05-2018",
        "ird updated at 03:54 PM 16-05-2018",
        "dob updated at 03:54 PM 16-05-2018"
      ],
      "procedures": [],
      "organsDonating": [
        "BONE_MARROW",
        "HEART",
        "BONE",
        "CONNECTIVE_TISSUE",
        "CORNEA"
      ],
      "organsDonated": [
        "BONE_MARROW",
        "BONE",
        "CONNECTIVE_TISSUE"
      ],
      "organsRequired": [
        "INTESTINE"
      ],
      "organsReceived": [],
      "conditions": [],
      "irdNumber": 903125559,
      "timeOfCreation": {
        "date": {
          "year": 2018,
          "month": 5,
          "day": 16
        },
        "time": {
          "hour": 15,
          "minute": 54,
          "second": 21,
          "nano": 252000000
        }
      },
      "lastUpdated": {
        "date": {
          "year": 2018,
          "month": 5,
          "day": 16
        },
        "time": {
          "hour": 15,
          "minute": 54,
          "second": 21,
          "nano": 252000000
        }
      },
      "id": 1,
      "currentMedications": [],
      "historyOfMedication": [],
      "medicationTimestamps": []
    },
    "2": {
      "donor": true,
      "receiver": true,
      "givenNames": "Boaty",
      "lastNames": "McBoatFace",
      "dateOfBirth": {
        "year": 1966,
        "month": 5,
        "day": 22
      },
      "chronicDiseases": [],
      "updateActions": [
        "given-names updated at 03:54 PM 16-05-2018",
        "last-names updated at 03:54 PM 16-05-2018",
        "ird updated at 03:54 PM 16-05-2018",
        "dob updated at 03:54 PM 16-05-2018"
      ],
      "procedures": [],
      "organsDonating": [
        "INTESTINE",
        "BONE_MARROW",
        "HEART",
        "BONE",
        "CONNECTIVE_TISSUE",
        "CORNEA"
      ],
      "organsDonated": [
        "BONE_MARROW",
        "BONE"
      ],
      "organsRequired": [],
      "organsReceived": [],
      "conditions": [],
      "irdNumber": 524348671,
      "timeOfCreation": {
        "date": {
          "year": 2018,
          "month": 5,
          "day": 16
        },
        "time": {
          "hour": 15,
          "minute": 54,
          "second": 21,
          "nano": 253000000
        }
      },
      "lastUpdated": {
        "date": {
          "year": 2018,
          "month": 5,
          "day": 16
        },
        "time": {
          "hour": 15,
          "minute": 54,
          "second": 21,
          "nano": 253000000
        }
      },
      "id": 2,
      "currentMedications": [],
      "historyOfMedication": [],
      "medicationTimestamps": []
    },
    "3": {
      "donor": true,
      "receiver": true,
      "givenNames": "Boobafina",
      "lastNames": "Otter",
      "dateOfBirth": {
        "year": 1932,
        "month": 4,
        "day": 22
      },
      "chronicDiseases": [],
      "updateActions": [
        "given-names updated at 03:54 PM 16-05-2018",
        "last-names updated at 03:54 PM 16-05-2018",
        "ird updated at 03:54 PM 16-05-2018",
        "dob updated at 03:54 PM 16-05-2018"
      ],
      "procedures": [],
      "organsDonating": [
        "INTESTINE",
        "BONE_MARROW",
        "HEART",
        "BONE",
        "CONNECTIVE_TISSUE",
        "CORNEA",
        "KIDNEY"
      ],
      "organsDonated": [],
      "organsRequired": [],
      "organsReceived": [],
      "conditions": [],
      "irdNumber": 540886877,
      "timeOfCreation": {
        "date": {
          "year": 2018,
          "month": 5,
          "day": 16
        },
        "time": {
          "hour": 15,
          "minute": 54,
          "second": 21,
          "nano": 253000000
        }
      },
      "lastUpdated": {
        "date": {
          "year": 2018,
          "month": 5,
          "day": 16
        },
        "time": {
          "hour": 15,
          "minute": 54,
          "second": 21,
          "nano": 253000000
        }
      },
      "id": 3,
      "currentMedications": [],
      "historyOfMedication": [],
      "medicationTimestamps": []
    },
    "4": {
      "donor": true,
      "receiver": true,
      "givenNames": "Chewy",
      "lastNames": "Pancake",
      "dateOfBirth": {
        "year": 1941,
        "month": 1,
        "day": 1
      },
      "chronicDiseases": [],
      "updateActions": [
        "given-names updated at 03:54 PM 16-05-2018",
        "last-names updated at 03:54 PM 16-05-2018",
        "ird updated at 03:54 PM 16-05-2018",
        "dob updated at 03:54 PM 16-05-2018"
      ],
      "procedures": [],
      "organsDonating": [
        "BONE"
      ],
      "organsDonated": [
        "INTESTINE",
        "MIDDLE_EAR",
        "BONE_MARROW",
        "HEART",
        "BONE",
        "CONNECTIVE_TISSUE",
        "PANCREAS",
        "CORNEA",
        "LIVER",
        "LUNG",
        "KIDNEY"
      ],
      "organsRequired": [
        "INTESTINE",
        "BONE_MARROW",
        "HEART",
        "CONNECTIVE_TISSUE",
        "CORNEA",
        "LIVER",
        "KIDNEY"
      ],
      "organsReceived": [],
      "conditions": [],
      "irdNumber": 892526982,
      "timeOfCreation": {
        "date": {
          "year": 2018,
          "month": 5,
          "day": 16
        },
        "time": {
          "hour": 15,
          "minute": 54,
          "second": 21,
          "nano": 254000000
        }
      },
      "lastUpdated": {
        "date": {
          "year": 2018,
          "month": 5,
          "day": 16
        },
        "time": {
          "hour": 15,
          "minute": 54,
          "second": 21,
          "nano": 254000000
        }
      },
      "id": 4,
      "currentMedications": [],
      "historyOfMedication": [],
      "medicationTimestamps": []
    },
    "5": {
      "donor": true,
      "receiver": true,
      "givenNames": "Cloud",
      "lastNames": "Strife",
      "dateOfBirth": {
        "year": 1920,
        "month": 1,
        "day": 1
      },
      "chronicDiseases": [],
      "updateActions": [
        "given-names updated at 03:54 PM 16-05-2018",
        "last-names updated at 03:54 PM 16-05-2018",
        "ird updated at 03:54 PM 16-05-2018",
        "dob updated at 03:54 PM 16-05-2018"
      ],
      "procedures": [],
      "organsDonating": [],
      "organsDonated": [
        "INTESTINE",
        "BONE_MARROW",
        "HEART",
        "BONE",
        "CONNECTIVE_TISSUE",
        "CORNEA",
        "LIVER",
        "LUNG",
        "KIDNEY"
      ],
      "organsRequired": [
        "INTESTINE",
        "BONE_MARROW",
        "HEART",
        "BONE",
        "CONNECTIVE_TISSUE",
        "CORNEA",
        "LIVER",
        "LUNG",
        "KIDNEY"
      ],
      "organsReceived": [],
      "conditions": [],
      "irdNumber": 480499416,
      "timeOfCreation": {
        "date": {
          "year": 2018,
          "month": 5,
          "day": 16
        },
        "time": {
          "hour": 15,
          "minute": 54,
          "second": 21,
          "nano": 254000000
        }
      },
      "lastUpdated": {
        "date": {
          "year": 2018,
          "month": 5,
          "day": 16
        },
        "time": {
          "hour": 15,
          "minute": 54,
          "second": 21,
          "nano": 254000000
        }
      },
      "id": 5,
      "currentMedications": [],
      "historyOfMedication": [],
      "medicationTimestamps": []
    },
    "6": {
      "donor": true,
      "receiver": true,
      "givenNames": "Darbage",
      "lastNames": "Gumpster",
      "dateOfBirth": {
        "year": 1952,
        "month": 12,
        "day": 22
      },
      "chronicDiseases": [],
      "updateActions": [
        "given-names updated at 03:54 PM 16-05-2018",
        "last-names updated at 03:54 PM 16-05-2018",
        "ird updated at 03:54 PM 16-05-2018",
        "dob updated at 03:54 PM 16-05-2018"
      ],
      "procedures": [],
      "organsDonating": [
        "INTESTINE",
        "BONE_MARROW",
        "HEART",
        "BONE",
        "CONNECTIVE_TISSUE",
        "CORNEA",
        "LIVER",
        "KIDNEY"
      ],
      "organsDonated": [
        "INTESTINE",
        "BONE_MARROW",
        "HEART",
        "BONE",
        "CONNECTIVE_TISSUE",
        "CORNEA",
        "KIDNEY"
      ],
      "organsRequired": [
        "MIDDLE_EAR",
        "LUNG"
      ],
      "organsReceived": [],
      "conditions": [],
      "irdNumber": 765367283,
      "timeOfCreation": {
        "date": {
          "year": 2018,
          "month": 5,
          "day": 16
        },
        "time": {
          "hour": 15,
          "minute": 54,
          "second": 21,
          "nano": 255000000
        }
      },
      "lastUpdated": {
        "date": {
          "year": 2018,
          "month": 5,
          "day": 16
        },
        "time": {
          "hour": 15,
          "minute": 54,
          "second": 21,
          "nano": 255000000
        }
      },
      "id": 6,
      "currentMedications": [],
      "historyOfMedication": [],
      "medicationTimestamps": []
    },
    "7": {
      "donor": true,
      "receiver": true,
      "givenNames": "Fried",
      "lastNames": "McChicken",
      "dateOfBirth": {
        "year": 2002,
        "month": 10,
        "day": 29
      },
      "chronicDiseases": [],
      "updateActions": [
        "given-names updated at 03:54 PM 16-05-2018",
        "last-names updated at 03:54 PM 16-05-2018",
        "ird updated at 03:54 PM 16-05-2018",
        "dob updated at 03:54 PM 16-05-2018"
      ],
      "procedures": [],
      "organsDonating": [
        "INTESTINE",
        "MIDDLE_EAR",
        "BONE_MARROW",
        "HEART",
        "BONE",
        "CONNECTIVE_TISSUE",
        "CORNEA",
        "LIVER",
        "LUNG",
        "KIDNEY"
      ],
      "organsDonated": [
        "BONE_MARROW",
        "BONE",
        "CONNECTIVE_TISSUE",
        "CORNEA"
      ],
      "organsRequired": [],
      "organsReceived": [],
      "conditions": [],
      "irdNumber": 271982666,
      "timeOfCreation": {
        "date": {
          "year": 2018,
          "month": 5,
          "day": 16
        },
        "time": {
          "hour": 15,
          "minute": 54,
          "second": 21,
          "nano": 255000000
        }
      },
      "lastUpdated": {
        "date": {
          "year": 2018,
          "month": 5,
          "day": 16
        },
        "time": {
          "hour": 15,
          "minute": 54,
          "second": 21,
          "nano": 255000000
        }
      },
      "id": 7,
      "currentMedications": [],
      "historyOfMedication": [],
      "medicationTimestamps": []
    },
    "8": {
      "donor": true,
      "receiver": true,
      "givenNames": "Galil",
      "lastNames": "AR",
      "dateOfBirth": {
        "year": 1977,
        "month": 9,
        "day": 21
      },
      "chronicDiseases": [],
      "updateActions": [
        "given-names updated at 03:54 PM 16-05-2018",
        "last-names updated at 03:54 PM 16-05-2018",
        "ird updated at 03:54 PM 16-05-2018",
        "dob updated at 03:54 PM 16-05-2018"
      ],
      "procedures": [],
      "organsDonating": [
        "BONE_MARROW",
        "BONE",
        "CONNECTIVE_TISSUE"
      ],
      "organsDonated": [
        "INTESTINE",
        "MIDDLE_EAR",
        "BONE_MARROW",
        "HEART",
        "BONE",
        "CONNECTIVE_TISSUE",
        "PANCREAS",
        "CORNEA",
        "LIVER",
        "LUNG",
        "KIDNEY"
      ],
      "organsRequired": [
        "HEART",
        "CORNEA"
      ],
      "organsReceived": [],
      "conditions": [
        {
          "name": "Heart Disease",
          "dateOfDiagnosis": {
            "year": 2018,
            "month": 4,
            "day": 1
          },
          "isCured": false,
          "isChronic": true,
          "chronicText": "CHRONIC"
        },
        {
          "name": "Heart Palpitations",
          "dateOfDiagnosis": {
            "year": 2018,
            "month": 3,
            "day": 1
          },
          "dateCured": {
            "year": 2018,
            "month": 4,
            "day": 1
          },
          "isCured": true,
          "isChronic": false,
          "chronicText": ""
        }
      ],
      "irdNumber": 322325871,
      "timeOfCreation": {
        "date": {
          "year": 2018,
          "month": 5,
          "day": 16
        },
        "time": {
          "hour": 15,
          "minute": 54,
          "second": 21,
          "nano": 256000000
        }
      },
      "lastUpdated": {
        "date": {
          "year": 2018,
          "month": 5,
          "day": 16
        },
        "time": {
          "hour": 15,
          "minute": 54,
          "second": 21,
          "nano": 256000000
        }
      },
      "id": 8,
      "currentMedications": [],
      "historyOfMedication": [],
      "medicationTimestamps": []
    },
    "9": {
      "donor": true,
      "receiver": true,
      "givenNames": "Gordon",
      "lastNames": "Freeman",
      "dateOfBirth": {
        "year": 1932,
        "month": 6,
        "day": 29
      },
      "chronicDiseases": [],
      "updateActions": [
        "given-names updated at 03:54 PM 16-05-2018",
        "last-names updated at 03:54 PM 16-05-2018",
        "ird updated at 03:54 PM 16-05-2018",
        "dob updated at 03:54 PM 16-05-2018"
      ],
      "procedures": [],
      "organsDonating": [
        "INTESTINE",
        "BONE_MARROW",
        "HEART",
        "BONE",
        "CONNECTIVE_TISSUE",
        "CORNEA",
        "KIDNEY"
      ],
      "organsDonated": [],
      "organsRequired": [
        "MIDDLE_EAR",
        "PANCREAS",
        "LIVER",
        "LUNG"
      ],
      "organsReceived": [],
      "conditions": [],
      "irdNumber": 209436113,
      "timeOfCreation": {
        "date": {
          "year": 2018,
          "month": 5,
          "day": 16
        },
        "time": {
          "hour": 15,
          "minute": 54,
          "second": 21,
          "nano": 256000000
        }
      },
      "lastUpdated": {
        "date": {
          "year": 2018,
          "month": 5,
          "day": 16
        },
        "time": {
          "hour": 15,
          "minute": 54,
          "second": 21,
          "nano": 256000000
        }
      },
      "id": 9,
      "currentMedications": [],
      "historyOfMedication": [],
      "medicationTimestamps": []
    },
    "10": {
      "donor": true,
      "receiver": true,
      "givenNames": "Hadron",
      "lastNames": "Collider",
      "dateOfBirth": {
        "year": 1907,
        "month": 1,
        "day": 3
      },
      "chronicDiseases": [],
      "updateActions": [
        "given-names updated at 03:54 PM 16-05-2018",
        "last-names updated at 03:54 PM 16-05-2018",
        "ird updated at 03:54 PM 16-05-2018",
        "dob updated at 03:54 PM 16-05-2018"
      ],
      "procedures": [],
      "organsDonating": [
        "INTESTINE",
        "BONE_MARROW",
        "HEART",
        "BONE",
        "CONNECTIVE_TISSUE",
        "CORNEA"
      ],
      "organsDonated": [
        "INTESTINE",
        "MIDDLE_EAR",
        "BONE_MARROW",
        "HEART",
        "BONE",
        "CONNECTIVE_TISSUE",
        "CORNEA",
        "LIVER",
        "LUNG",
        "KIDNEY"
      ],
      "organsRequired": [
        "LIVER",
        "LUNG",
        "KIDNEY"
      ],
      "organsReceived": [],
      "conditions": [],
      "irdNumber": 421972099,
      "timeOfCreation": {
        "date": {
          "year": 2018,
          "month": 5,
          "day": 16
        },
        "time": {
          "hour": 15,
          "minute": 54,
          "second": 21,
          "nano": 257000000
        }
      },
      "lastUpdated": {
        "date": {
          "year": 2018,
          "month": 5,
          "day": 16
        },
        "time": {
          "hour": 15,
          "minute": 54,
          "second": 21,
          "nano": 257000000
        }
      },
      "id": 10,
      "currentMedications": [],
      "historyOfMedication": [],
      "medicationTimestamps": []
    },
    "11": {
      "donor": true,
      "receiver": true,
      "givenNames": "Hato",
      "lastNames": "Pigeon",
      "dateOfBirth": {
        "year": 1964,
        "month": 1,
        "day": 15
      },
      "chronicDiseases": [],
      "updateActions": [
        "given-names updated at 03:54 PM 16-05-2018",
        "last-names updated at 03:54 PM 16-05-2018",
        "ird updated at 03:54 PM 16-05-2018",
        "dob updated at 03:54 PM 16-05-2018"
      ],
      "procedures": [],
      "organsDonating": [
        "INTESTINE",
        "BONE_MARROW",
        "HEART",
        "BONE",
        "CONNECTIVE_TISSUE",
        "CORNEA",
        "LIVER",
        "LUNG",
        "KIDNEY"
      ],
      "organsDonated": [
        "BONE_MARROW",
        "BONE"
      ],
      "organsRequired": [],
      "organsReceived": [],
      "conditions": [],
      "irdNumber": 373881261,
      "timeOfCreation": {
        "date": {
          "year": 2018,
          "month": 5,
          "day": 16
        },
        "time": {
          "hour": 15,
          "minute": 54,
          "second": 21,
          "nano": 257000000
        }
      },
      "lastUpdated": {
        "date": {
          "year": 2018,
          "month": 5,
          "day": 16
        },
        "time": {
          "hour": 15,
          "minute": 54,
          "second": 21,
          "nano": 257000000
        }
      },
      "id": 11,
      "currentMedications": [],
      "historyOfMedication": [],
      "medicationTimestamps": []
    },
    "12": {
      "donor": true,
      "receiver": true,
      "givenNames": "Hojn",
      "lastNames": "Bjorn",
      "dateOfBirth": {
        "year": 1935,
        "month": 4,
        "day": 5
      },
      "chronicDiseases": [],
      "updateActions": [
        "given-names updated at 03:54 PM 16-05-2018",
        "last-names updated at 03:54 PM 16-05-2018",
        "ird updated at 03:54 PM 16-05-2018",
        "dob updated at 03:54 PM 16-05-2018"
      ],
      "procedures": [],
      "organsDonating": [
        "INTESTINE",
        "BONE_MARROW",
        "HEART",
        "BONE",
        "CONNECTIVE_TISSUE",
        "CORNEA",
        "LIVER",
        "KIDNEY"
      ],
      "organsDonated": [
        "BONE_MARROW",
        "BONE",
        "CONNECTIVE_TISSUE"
      ],
      "organsRequired": [],
      "organsReceived": [],
      "conditions": [],
      "irdNumber": 715400751,
      "timeOfCreation": {
        "date": {
          "year": 2018,
          "month": 5,
          "day": 16
        },
        "time": {
          "hour": 15,
          "minute": 54,
          "second": 21,
          "nano": 258000000
        }
      },
      "lastUpdated": {
        "date": {
          "year": 2018,
          "month": 5,
          "day": 16
        },
        "time": {
          "hour": 15,
          "minute": 54,
          "second": 21,
          "nano": 258000000
        }
      },
      "id": 12,
      "currentMedications": [],
      "historyOfMedication": [],
      "medicationTimestamps": []
    },
    "13": {
      "donor": true,
      "receiver": false,
      "givenNames": "Jake",
      "lastNames": "Dogg",
      "dateOfBirth": {
        "year": 1963,
        "month": 12,
        "day": 7
      },
      "chronicDiseases": [],
      "updateActions": [
        "given-names updated at 03:54 PM 16-05-2018",
        "last-names updated at 03:54 PM 16-05-2018",
        "ird updated at 03:54 PM 16-05-2018",
        "dob updated at 03:54 PM 16-05-2018"
      ],
      "procedures": [],
      "organsDonating": [
        "INTESTINE",
        "BONE_MARROW",
        "HEART",
        "BONE",
        "CONNECTIVE_TISSUE",
        "CORNEA",
        "KIDNEY"
      ],
      "organsDonated": [
        "BONE"
      ],
      "organsRequired": [],
      "organsReceived": [],
      "conditions": [],
      "irdNumber": 362822415,
      "timeOfCreation": {
        "date": {
          "year": 2018,
          "month": 5,
          "day": 16
        },
        "time": {
          "hour": 15,
          "minute": 54,
          "second": 21,
          "nano": 258000000
        }
      },
      "lastUpdated": {
        "date": {
          "year": 2018,
          "month": 5,
          "day": 16
        },
        "time": {
          "hour": 15,
          "minute": 54,
          "second": 21,
          "nano": 258000000
        }
      },
      "id": 13,
      "currentMedications": [],
      "historyOfMedication": [],
      "medicationTimestamps": []
    },
    "14": {
      "donor": true,
      "receiver": true,
      "givenNames": "John",
      "lastNames": "Wick",
      "dateOfBirth": {
        "year": 1941,
        "month": 10,
        "day": 18
      },
      "chronicDiseases": [],
      "updateActions": [
        "given-names updated at 03:54 PM 16-05-2018",
        "last-names updated at 03:54 PM 16-05-2018",
        "ird updated at 03:54 PM 16-05-2018",
        "dob updated at 03:54 PM 16-05-2018"
      ],
      "procedures": [],
      "organsDonating": [
        "BONE_MARROW",
        "HEART",
        "BONE",
        "CONNECTIVE_TISSUE",
        "CORNEA"
      ],
      "organsDonated": [
        "INTESTINE",
        "BONE_MARROW",
        "HEART",
        "BONE",
        "CONNECTIVE_TISSUE",
        "CORNEA",
        "LIVER",
        "LUNG",
        "KIDNEY"
      ],
      "organsRequired": [
        "INTESTINE",
        "KIDNEY"
      ],
      "organsReceived": [],
      "conditions": [],
      "irdNumber": 524981307,
      "timeOfCreation": {
        "date": {
          "year": 2018,
          "month": 5,
          "day": 16
        },
        "time": {
          "hour": 15,
          "minute": 54,
          "second": 21,
          "nano": 258000000
        }
      },
      "lastUpdated": {
        "date": {
          "year": 2018,
          "month": 5,
          "day": 16
        },
        "time": {
          "hour": 15,
          "minute": 54,
          "second": 21,
          "nano": 258000000
        }
      },
      "id": 14,
      "currentMedications": [],
      "historyOfMedication": [],
      "medicationTimestamps": []
    },
    "15": {
      "donor": true,
      "receiver": true,
      "givenNames": "Marcus",
      "lastNames": "Fenix",
      "dateOfBirth": {
        "year": 1993,
        "month": 2,
        "day": 16
      },
      "chronicDiseases": [],
      "updateActions": [
        "given-names updated at 03:54 PM 16-05-2018",
        "last-names updated at 03:54 PM 16-05-2018",
        "ird updated at 03:54 PM 16-05-2018",
        "dob updated at 03:54 PM 16-05-2018"
      ],
      "procedures": [],
      "organsDonating": [
        "BONE_MARROW",
        "BONE"
      ],
      "organsDonated": [
        "BONE_MARROW",
        "BONE",
        "CONNECTIVE_TISSUE"
      ],
      "organsRequired": [
        "CONNECTIVE_TISSUE"
      ],
      "organsReceived": [],
      "conditions": [],
      "irdNumber": 828564080,
      "timeOfCreation": {
        "date": {
          "year": 2018,
          "month": 5,
          "day": 16
        },
        "time": {
          "hour": 15,
          "minute": 54,
          "second": 21,
          "nano": 259000000
        }
      },
      "lastUpdated": {
        "date": {
          "year": 2018,
          "month": 5,
          "day": 16
        },
        "time": {
          "hour": 15,
          "minute": 54,
          "second": 21,
          "nano": 259000000
        }
      },
      "id": 15,
      "currentMedications": [],
      "historyOfMedication": [],
      "medicationTimestamps": []
    },
    "16": {
      "donor": true,
      "receiver": true,
      "givenNames": "Nathan",
      "lastNames": "Drake",
      "dateOfBirth": {
        "year": 1963,
        "month": 2,
        "day": 25
      },
      "chronicDiseases": [],
      "updateActions": [
        "given-names updated at 03:54 PM 16-05-2018",
        "last-names updated at 03:54 PM 16-05-2018",
        "ird updated at 03:54 PM 16-05-2018",
        "dob updated at 03:54 PM 16-05-2018"
      ],
      "procedures": [],
      "organsDonating": [
        "INTESTINE",
        "MIDDLE_EAR",
        "BONE_MARROW",
        "HEART",
        "BONE",
        "CONNECTIVE_TISSUE",
        "CORNEA",
        "LIVER",
        "LUNG",
        "KIDNEY"
      ],
      "organsDonated": [
        "BONE"
      ],
      "organsRequired": [],
      "organsReceived": [],
      "conditions": [],
      "irdNumber": 330184076,
      "timeOfCreation": {
        "date": {
          "year": 2018,
          "month": 5,
          "day": 16
        },
        "time": {
          "hour": 15,
          "minute": 54,
          "second": 21,
          "nano": 259000000
        }
      },
      "lastUpdated": {
        "date": {
          "year": 2018,
          "month": 5,
          "day": 16
        },
        "time": {
          "hour": 15,
          "minute": 54,
          "second": 21,
          "nano": 259000000
        }
      },
      "id": 16,
      "currentMedications": [],
      "historyOfMedication": [],
      "medicationTimestamps": []
    },
    "17": {
      "donor": true,
      "receiver": true,
      "givenNames": "Peppermint",
      "lastNames": "Butler",
      "dateOfBirth": {
        "year": 1964,
        "month": 4,
        "day": 24
      },
      "chronicDiseases": [],
      "updateActions": [
        "given-names updated at 03:54 PM 16-05-2018",
        "last-names updated at 03:54 PM 16-05-2018",
        "ird updated at 03:54 PM 16-05-2018",
        "dob updated at 03:54 PM 16-05-2018"
      ],
      "procedures": [],
      "organsDonating": [
        "BONE"
      ],
      "organsDonated": [
        "INTESTINE",
        "BONE_MARROW",
        "HEART",
        "BONE",
        "CONNECTIVE_TISSUE",
        "CORNEA",
        "LIVER",
        "LUNG",
        "KIDNEY"
      ],
      "organsRequired": [
        "BONE_MARROW"
      ],
      "organsReceived": [],
      "conditions": [],
      "irdNumber": 195042223,
      "timeOfCreation": {
        "date": {
          "year": 2018,
          "month": 5,
          "day": 16
        },
        "time": {
          "hour": 15,
          "minute": 54,
          "second": 21,
          "nano": 260000000
        }
      },
      "lastUpdated": {
        "date": {
          "year": 2018,
          "month": 5,
          "day": 16
        },
        "time": {
          "hour": 15,
          "minute": 54,
          "second": 21,
          "nano": 260000000
        }
      },
      "id": 17,
      "currentMedications": [],
      "historyOfMedication": [],
      "medicationTimestamps": []
    },
    "18": {
      "donor": true,
      "receiver": true,
      "givenNames": "Ronald",
      "lastNames": "McDonald",
      "dateOfBirth": {
        "year": 1910,
        "month": 7,
        "day": 5
      },
      "chronicDiseases": [],
      "updateActions": [
        "given-names updated at 03:54 PM 16-05-2018",
        "last-names updated at 03:54 PM 16-05-2018",
        "ird updated at 03:54 PM 16-05-2018",
        "dob updated at 03:54 PM 16-05-2018"
      ],
      "procedures": [],
      "organsDonating": [
        "BONE_MARROW",
        "BONE"
      ],
      "organsDonated": [
        "BONE_MARROW",
        "BONE"
      ],
      "organsRequired": [
        "INTESTINE",
        "HEART",
        "CONNECTIVE_TISSUE",
        "CORNEA",
        "LIVER",
        "KIDNEY"
      ],
      "organsReceived": [],
      "conditions": [],
      "irdNumber": 929694195,
      "timeOfCreation": {
        "date": {
          "year": 2018,
          "month": 5,
          "day": 16
        },
        "time": {
          "hour": 15,
          "minute": 54,
          "second": 21,
          "nano": 260000000
        }
      },
      "lastUpdated": {
        "date": {
          "year": 2018,
          "month": 5,
          "day": 16
        },
        "time": {
          "hour": 15,
          "minute": 54,
          "second": 21,
          "nano": 260000000
        }
      },
      "id": 18,
      "currentMedications": [],
      "historyOfMedication": [],
      "medicationTimestamps": []
    },
    "19": {
      "donor": true,
      "receiver": true,
      "givenNames": "Sammie",
      "lastNames": "Salmon",
      "dateOfBirth": {
        "year": 1927,
        "month": 5,
        "day": 20
      },
      "chronicDiseases": [],
      "updateActions": [
        "given-names updated at 03:54 PM 16-05-2018",
        "last-names updated at 03:54 PM 16-05-2018",
        "ird updated at 03:54 PM 16-05-2018",
        "dob updated at 03:54 PM 16-05-2018"
      ],
      "procedures": [],
      "organsDonating": [
        "BONE_MARROW",
        "BONE",
        "CONNECTIVE_TISSUE"
      ],
      "organsDonated": [
        "INTESTINE",
        "BONE_MARROW",
        "HEART",
        "BONE",
        "CONNECTIVE_TISSUE",
        "CORNEA",
        "KIDNEY"
      ],
      "organsRequired": [
        "HEART",
        "CORNEA"
      ],
      "organsReceived": [],
      "conditions": [],
      "irdNumber": 413631706,
      "timeOfCreation": {
        "date": {
          "year": 2018,
          "month": 5,
          "day": 16
        },
        "time": {
          "hour": 15,
          "minute": 54,
          "second": 21,
          "nano": 261000000
        }
      },
      "lastUpdated": {
        "date": {
          "year": 2018,
          "month": 5,
          "day": 16
        },
        "time": {
          "hour": 15,
          "minute": 54,
          "second": 21,
          "nano": 261000000
        }
      },
      "id": 19,
      "currentMedications": [],
      "historyOfMedication": [],
      "medicationTimestamps": []
    },
    "20": {
      "donor": true,
      "receiver": true,
      "givenNames": "Samus",
      "lastNames": "Aran",
      "dateOfBirth": {
        "year": 1943,
        "month": 7,
        "day": 27
      },
      "chronicDiseases": [],
      "updateActions": [
        "given-names updated at 03:54 PM 16-05-2018",
        "last-names updated at 03:54 PM 16-05-2018",
        "ird updated at 03:54 PM 16-05-2018",
        "dob updated at 03:54 PM 16-05-2018"
      ],
      "procedures": [],
      "organsDonating": [
        "BONE"
      ],
      "organsDonated": [
        "INTESTINE",
        "BONE_MARROW",
        "HEART",
        "BONE",
        "CONNECTIVE_TISSUE",
        "CORNEA",
        "KIDNEY"
      ],
      "organsRequired": [
        "BONE_MARROW",
        "HEART",
        "CONNECTIVE_TISSUE",
        "CORNEA"
      ],
      "organsReceived": [],
      "conditions": [],
      "irdNumber": 485546805,
      "timeOfCreation": {
        "date": {
          "year": 2018,
          "month": 5,
          "day": 16
        },
        "time": {
          "hour": 15,
          "minute": 54,
          "second": 21,
          "nano": 261000000
        }
      },
      "lastUpdated": {
        "date": {
          "year": 2018,
          "month": 5,
          "day": 16
        },
        "time": {
          "hour": 15,
          "minute": 54,
          "second": 21,
          "nano": 261000000
        }
      },
      "id": 20,
      "currentMedications": [],
      "historyOfMedication": [],
      "medicationTimestamps": []
    },
    "21": {
      "donor": true,
      "receiver": true,
      "givenNames": "Slim",
      "lastNames": "Flapjack",
      "dateOfBirth": {
        "year": 1951,
        "month": 4,
        "day": 13
      },
      "chronicDiseases": [],
      "updateActions": [
        "given-names updated at 03:54 PM 16-05-2018",
        "last-names updated at 03:54 PM 16-05-2018",
        "ird updated at 03:54 PM 16-05-2018",
        "dob updated at 03:54 PM 16-05-2018"
      ],
      "procedures": [],
      "organsDonating": [
        "BONE_MARROW",
        "BONE",
        "CONNECTIVE_TISSUE",
        "CORNEA"
      ],
      "organsDonated": [
        "BONE_MARROW",
        "HEART",
        "BONE",
        "CONNECTIVE_TISSUE",
        "CORNEA"
      ],
      "organsRequired": [
        "INTESTINE",
        "HEART",
        "LIVER",
        "KIDNEY"
      ],
      "organsReceived": [],
      "conditions": [],
      "irdNumber": 983640587,
      "timeOfCreation": {
        "date": {
          "year": 2018,
          "month": 5,
          "day": 16
        },
        "time": {
          "hour": 15,
          "minute": 54,
          "second": 21,
          "nano": 261000000
        }
      },
      "lastUpdated": {
        "date": {
          "year": 2018,
          "month": 5,
          "day": 16
        },
        "time": {
          "hour": 15,
          "minute": 54,
          "second": 21,
          "nano": 261000000
        }
      },
      "id": 21,
      "currentMedications": [],
      "historyOfMedication": [],
      "medicationTimestamps": []
    },
    "22": {
      "donor": true,
      "receiver": true,
      "givenNames": "Snoop",
      "lastNames": "Dogg",
      "dateOfBirth": {
        "year": 2014,
        "month": 4,
        "day": 18
      },
      "chronicDiseases": [],
      "updateActions": [
        "given-names updated at 03:54 PM 16-05-2018",
        "last-names updated at 03:54 PM 16-05-2018",
        "ird updated at 03:54 PM 16-05-2018",
        "dob updated at 03:54 PM 16-05-2018"
      ],
      "procedures": [],
      "organsDonating": [
        "INTESTINE",
        "BONE_MARROW",
        "HEART",
        "BONE",
        "CONNECTIVE_TISSUE",
        "CORNEA",
        "LIVER",
        "KIDNEY"
      ],
      "organsDonated": [
        "INTESTINE",
        "BONE_MARROW",
        "HEART",
        "BONE",
        "CONNECTIVE_TISSUE",
        "CORNEA",
        "LIVER",
        "LUNG",
        "KIDNEY"
      ],
      "organsRequired": [],
      "organsReceived": [],
      "conditions": [],
      "irdNumber": 655933435,
      "timeOfCreation": {
        "date": {
          "year": 2018,
          "month": 5,
          "day": 16
        },
        "time": {
          "hour": 15,
          "minute": 54,
          "second": 21,
          "nano": 262000000
        }
      },
      "lastUpdated": {
        "date": {
          "year": 2018,
          "month": 5,
          "day": 16
        },
        "time": {
          "hour": 15,
          "minute": 54,
          "second": 21,
          "nano": 262000000
        }
      },
      "id": 22,
      "currentMedications": [],
      "historyOfMedication": [],
      "medicationTimestamps": []
    },
    "23": {
      "donor": true,
      "receiver": true,
      "givenNames": "Vorian",
      "lastNames": "Atreides",
      "dateOfBirth": {
        "year": 1923,
        "month": 4,
        "day": 10
      },
      "chronicDiseases": [],
      "updateActions": [
        "given-names updated at 03:54 PM 16-05-2018",
        "last-names updated at 03:54 PM 16-05-2018",
        "ird updated at 03:54 PM 16-05-2018",
        "dob updated at 03:54 PM 16-05-2018"
      ],
      "procedures": [],
      "organsDonating": [
        "INTESTINE",
        "BONE_MARROW",
        "HEART",
        "BONE",
        "CONNECTIVE_TISSUE",
        "CORNEA",
        "KIDNEY"
      ],
      "organsDonated": [
        "INTESTINE",
        "MIDDLE_EAR",
        "BONE_MARROW",
        "HEART",
        "BONE",
        "CONNECTIVE_TISSUE",
        "PANCREAS",
        "CORNEA",
        "LIVER",
        "LUNG",
        "KIDNEY"
      ],
      "organsRequired": [],
      "organsReceived": [],
      "conditions": [],
      "irdNumber": 319345159,
      "timeOfCreation": {
        "date": {
          "year": 2018,
          "month": 5,
          "day": 16
        },
        "time": {
          "hour": 15,
          "minute": 54,
          "second": 21,
          "nano": 262000000
        }
      },
      "lastUpdated": {
        "date": {
          "year": 2018,
          "month": 5,
          "day": 16
        },
        "time": {
          "hour": 15,
          "minute": 54,
          "second": 21,
          "nano": 262000000
        }
      },
      "id": 23,
      "currentMedications": [],
      "historyOfMedication": [],
      "medicationTimestamps": []
    },
    "24": {
      "donor": true,
      "receiver": true,
      "givenNames": "Xavier",
      "lastNames": "Harkonnen",
      "dateOfBirth": {
        "year": 1941,
        "month": 2,
        "day": 9
      },
      "chronicDiseases": [],
      "updateActions": [
        "given-names updated at 03:54 PM 16-05-2018",
        "last-names updated at 03:54 PM 16-05-2018",
        "ird updated at 03:54 PM 16-05-2018",
        "dob updated at 03:54 PM 16-05-2018"
      ],
      "procedures": [],
      "organsDonating": [
        "INTESTINE",
        "BONE_MARROW",
        "HEART",
        "BONE",
        "CONNECTIVE_TISSUE",
        "CORNEA",
        "LIVER",
        "LUNG",
        "KIDNEY"
      ],
      "organsDonated": [
        "INTESTINE",
        "BONE_MARROW",
        "HEART",
        "BONE",
        "CONNECTIVE_TISSUE",
        "CORNEA",
        "LIVER",
        "KIDNEY"
      ],
      "organsRequired": [],
      "organsReceived": [],
      "conditions": [],
      "irdNumber": 146739618,
      "timeOfCreation": {
        "date": {
          "year": 2018,
          "month": 5,
          "day": 16
        },
        "time": {
          "hour": 15,
          "minute": 54,
          "second": 21,
          "nano": 263000000
        }
      },
      "lastUpdated": {
        "date": {
          "year": 2018,
          "month": 5,
          "day": 16
        },
        "time": {
          "hour": 15,
          "minute": 54,
          "second": 21,
          "nano": 263000000
        }
      },
      "id": 24,
      "currentMedications": [],
      "historyOfMedication": [],
      "medicationTimestamps": []
    },
    "25": {
      "receiver": false,
      "givenNames": "Jack Travis",
      "lastNames": "Hay",
      "dateOfBirth": {
        "year": 1997,
        "month": 11,
        "day": 14
      },
      "chronicDiseases": [],
      "updateActions": [
        "given-names updated at 03:54 PM 16-05-2018",
        "last-names updated at 03:54 PM 16-05-2018",
        "ird updated at 03:54 PM 16-05-2018",
        "dob updated at 03:54 PM 16-05-2018"
      ],
      "procedures": [],
      "organsDonating": [],
      "organsDonated": [],
      "organsRequired": [],
      "organsReceived": [],
      "conditions": [],
      "irdNumber": 100132122,
      "timeOfCreation": {
        "date": {
          "year": 2018,
          "month": 5,
          "day": 16
        },
        "time": {
          "hour": 15,
          "minute": 54,
          "second": 30,
          "nano": 509000000
        }
      },
      "lastUpdated": {
        "date": {
          "year": 2018,
          "month": 5,
          "day": 16
        },
        "time": {
          "hour": 15,
          "minute": 54,
          "second": 30,
          "nano": 509000000
        }
      },
      "id": 25,
      "currentMedications": [],
      "historyOfMedication": [],
      "medicationTimestamps": []
    },
    "26": {
      "receiver": false,
      "givenNames": "Jack Travis",
      "lastNames": "Hay",
      "dateOfBirth": {
        "year": 1997,
        "month": 11,
        "day": 14
      },
      "chronicDiseases": [],
      "updateActions": [
        "given-names updated at 03:54 PM 16-05-2018",
        "last-names updated at 03:54 PM 16-05-2018",
        "ird updated at 03:54 PM 16-05-2018",
        "dob updated at 03:54 PM 16-05-2018"
      ],
      "procedures": [],
      "organsDonating": [],
      "organsDonated": [],
      "organsRequired": [],
      "organsReceived": [],
      "conditions": [],
      "irdNumber": 88888888,
      "timeOfCreation": {
        "date": {
          "year": 2018,
          "month": 5,
          "day": 16
        },
        "time": {
          "hour": 15,
          "minute": 54,
          "second": 41,
          "nano": 741000000
        }
      },
      "lastUpdated": {
        "date": {
          "year": 2018,
          "month": 5,
          "day": 16
        },
        "time": {
          "hour": 15,
          "minute": 54,
          "second": 41,
          "nano": 741000000
        }
      },
      "id": 26,
      "currentMedications": [],
      "historyOfMedication": [],
      "medicationTimestamps": []
    }
  },
  "deletedProfiles": [],
  "lastID": 26,
  "path": "example/example.json"
}