{"userDb":{"0":{"userType":"CLINICIAN","name":"John Smith","staffId":0,"region":"Christchurch","lastUpdated":{"date":{"year":2018,"month":4,"day":26},"time":{"hour":16,"minute":2,"second":11,"nano":893000000}},"updateActions":["Account for John Smithcreated at 2018-04-26T16:02:11.893","0 updated at 04:02 PM 26-04-2018"],"timeOfCreation":{"date":{"year":2018,"month":4,"day":26},"time":{"hour":16,"minute":2,"second":11,"nano":893000000}}},"1":{"userType":"CLINICIAN","name":"Matt Smith","staffId":1,"region":"Auckland","lastUpdated":{"date":{"year":2018,"month":4,"day":26},"time":{"hour":16,"minute":2,"second":11,"nano":894000000}},"updateActions":["Account for Matt Smithcreated at 2018-04-26T16:02:11.893","1 updated at 04:02 PM 26-04-2018"],"timeOfCreation":{"date":{"year":2018,"month":4,"day":26},"time":{"hour":16,"minute":2,"second":11,"nano":893000000}}}},"lastID":1}